{
  "updated_at": "2026-06-12 12:44 HKT",
  "weekends": [
    {
      "label": "6/19–21",
      "checkin": "2026-06-19",
      "checkout": "2026-06-21"
    },
    {
      "label": "6/26–28",
      "checkin": "2026-06-26",
      "checkout": "2026-06-28"
    },
    {
      "label": "7/3–5",
      "checkin": "2026-07-03",
      "checkout": "2026-07-05"
    }
  ],
  "cities": [
    {
      "key": "okinawa_south",
      "name": "沖繩南部・那霸",
      "flag": "🇯🇵",
      "weekend_hotels": [
        [
          {
            "name": "Aqua Citta酒店 那覇",
            "price": 1417,
            "rating": 8.6,
            "stars": 4
          },
          {
            "name": "諾富特沖繩那覇",
            "price": 1810,
            "rating": 8.6,
            "stars": 4
          }
        ],
        [
          {
            "name": "諾富特沖繩那覇",
            "price": 1527,
            "rating": 8.6,
            "stars": 4
          },
          {
            "name": "沖繩NaHaNa酒店&水療",
            "price": 1647,
            "rating": 8.1,
            "stars": 4
          }
        ],
        [
          {
            "name": "Nest酒店 那覇西",
            "price": 1699,
            "rating": 8.6,
            "stars": 4
          },
          {
            "name": "諾富特沖繩那覇",
            "price": 1923,
            "rating": 8.6,
            "stars": 4
          }
        ]
      ]
    },
    {
      "key": "okinawa_central",
      "name": "沖繩中部",
      "flag": "🇯🇵",
      "weekend_hotels": [
        [
          {
            "name": "Okinawa Kariyushi Beach Resort Ocean Spa",
            "price": 2383,
            "rating": 7.8,
            "stars": 4
          },
          {
            "name": "Rizzan Sea Park Hotel Tancha Bay",
            "price": 3937,
            "rating": 8.1,
            "stars": 4
          }
        ],
        [
          {
            "name": "Okinawa Kariyushi Beach Resort Ocean Spa",
            "price": 3312,
            "rating": 7.8,
            "stars": 4
          },
          {
            "name": "Rizzan Sea Park Hotel Tancha Bay",
            "price": 3377,
            "rating": 8.1,
            "stars": 4
          }
        ],
        [
          {
            "name": "Okinawa Kariyushi Beach Resort Ocean Spa",
            "price": 3272,
            "rating": 7.8,
            "stars": 4
          },
          {
            "name": "Rizzan Sea Park Hotel Tancha Bay",
            "price": 3835,
            "rating": 8.1,
            "stars": 4
          }
        ]
      ]
    },
    {
      "key": "okinawa_north",
      "name": "沖繩北部",
      "flag": "🇯🇵",
      "weekend_hotels": [
        [
          {
            "name": "Best Western Okinawa Kouki Beach",
            "price": 1733,
            "rating": 8.8,
            "stars": 4
          },
          {
            "name": "TWIN LINE HOTEL YANBARU OKINAWA JAPAN Formerly Okinawa Suncoast Hotel",
            "price": 3044,
            "rating": 9.0,
            "stars": 4
          }
        ],
        [
          {
            "name": "TWIN LINE HOTEL YANBARU OKINAWA JAPAN Formerly Okinawa Suncoast Hotel",
            "price": 2940,
            "rating": 9.0,
            "stars": 4
          },
          {
            "name": "Best Western Okinawa Kouki Beach",
            "price": 3344,
            "rating": 8.8,
            "stars": 4
          }
        ],
        [
          {
            "name": "Condominium NOOSA",
            "price": 9034,
            "rating": 9.9,
            "stars": 4
          },
          {
            "name": "Pool Villa Yagaji Island by Coldio Premium",
            "price": 9414,
            "rating": 9.4,
            "stars": 4
          }
        ]
      ]
    },
    {
      "key": "ishigaki",
      "name": "石垣島",
      "flag": "🇯🇵",
      "weekend_hotels": [
        [
          {
            "name": "Palm Villa石垣島",
            "price": 4843,
            "rating": 9.6,
            "stars": 4
          },
          {
            "name": "deigo ISHIGAKI",
            "price": 8438,
            "rating": 10.0,
            "stars": 4
          }
        ],
        [
          {
            "name": "deigo ISHIGAKI",
            "price": 8438,
            "rating": 10.0,
            "stars": 4
          }
        ],
        [
          {
            "name": "Palm Villa石垣島",
            "price": 5841,
            "rating": 9.6,
            "stars": 4
          },
          {
            "name": "deigo ISHIGAKI",
            "price": 8438,
            "rating": 10.0,
            "stars": 4
          }
        ]
      ]
    },
    {
      "key": "miyakojima",
      "name": "宮古島",
      "flag": "🇯🇵",
      "weekend_hotels": [
        [
          {
            "name": "Allamanda伊武野珊瑚村",
            "price": 5750,
            "rating": 9.0,
            "stars": 4
          },
          {
            "name": "SANTORINI HOTEL&VILLAS MIYAKOJIMA",
            "price": 6375,
            "rating": 9.6,
            "stars": 4
          }
        ],
        [
          {
            "name": "宮古島東急飯店",
            "price": 8589,
            "rating": 9.2,
            "stars": 4
          },
          {
            "name": "SANTORINI HOTEL&VILLAS MIYAKOJIMA",
            "price": 9000,
            "rating": 9.6,
            "stars": 4
          }
        ],
        [
          {
            "name": "SANTORINI HOTEL&VILLAS MIYAKOJIMA",
            "price": 6750,
            "rating": 9.6,
            "stars": 4
          },
          {
            "name": "Allamanda伊武野珊瑚村",
            "price": 9105,
            "rating": 9.0,
            "stars": 4
          }
        ]
      ]
    },
    {
      "key": "fukuoka",
      "name": "福岡",
      "flag": "🇯🇵",
      "weekend_hotels": [
        [
          {
            "name": "JAL城市酒店 福岡天神",
            "price": 3184,
            "rating": 8.8,
            "stars": 4
          },
          {
            "name": "ANA Crowne Plaza Fukuoka by IHG",
            "price": 3232,
            "rating": 8.1,
            "stars": 4
          }
        ],
        [
          {
            "name": "JAL城市酒店 福岡天神",
            "price": 2821,
            "rating": 8.8,
            "stars": 4
          },
          {
            "name": "ANA Crowne Plaza Fukuoka by IHG",
            "price": 2993,
            "rating": 8.1,
            "stars": 4
          }
        ],
        [
          {
            "name": "ANA Crowne Plaza Fukuoka by IHG",
            "price": 2858,
            "rating": 8.1,
            "stars": 4
          },
          {
            "name": "JAL城市酒店 福岡天神",
            "price": 2982,
            "rating": 8.8,
            "stars": 4
          }
        ]
      ]
    },
    {
      "key": "tokyo",
      "name": "東京",
      "flag": "🇯🇵",
      "weekend_hotels": [
        [
          {
            "name": "Villa Fontaine 羽田機場",
            "price": 2168,
            "rating": 8.7,
            "stars": 4
          },
          {
            "name": "The Royal Park Hotel Tokyo Haneda Airport Terminal 3",
            "price": 2318,
            "rating": 8.4,
            "stars": 4
          }
        ],
        [
          {
            "name": "Villa Fontaine 羽田機場",
            "price": 1914,
            "rating": 8.7,
            "stars": 4
          },
          {
            "name": "The Royal Park Hotel Tokyo Haneda Airport Terminal 3",
            "price": 2120,
            "rating": 8.4,
            "stars": 4
          }
        ],
        [
          {
            "name": "Villa Fontaine 羽田機場",
            "price": 2346,
            "rating": 8.7,
            "stars": 4
          },
          {
            "name": "The Royal Park Hotel Tokyo Haneda Airport Terminal 3",
            "price": 2438,
            "rating": 8.4,
            "stars": 4
          }
        ]
      ]
    },
    {
      "key": "seoul",
      "name": "首爾",
      "flag": "🇰🇷",
      "weekend_hotels": [
        [
          {
            "name": "Arirang Hill Hotel Dongdaemun",
            "price": 3401,
            "rating": 9.2,
            "stars": 4
          },
          {
            "name": "GLAD麻浦酒店",
            "price": 4913,
            "rating": 9.8,
            "stars": 4
          }
        ],
        [
          {
            "name": "Arirang Hill Hotel Dongdaemun",
            "price": 2656,
            "rating": 9.2,
            "stars": 4
          },
          {
            "name": "樂天城市酒店 明洞",
            "price": 3599,
            "rating": 8.8,
            "stars": 4
          }
        ],
        [
          {
            "name": "ibis Styles Ambassador Seoul Myeong-dong",
            "price": 2505,
            "rating": 9.2,
            "stars": 4
          },
          {
            "name": "Arirang Hill Hotel Dongdaemun",
            "price": 2639,
            "rating": 9.2,
            "stars": 4
          }
        ]
      ]
    },
    {
      "key": "busan",
      "name": "釜山",
      "flag": "🇰🇷",
      "weekend_hotels": [
        [
          {
            "name": "Avani Central Busan",
            "price": 1707,
            "rating": 9.2,
            "stars": 4
          },
          {
            "name": "Lavalse Hotel",
            "price": 1854,
            "rating": 8.4,
            "stars": 4
          }
        ],
        [
          {
            "name": "Haeundae Centum Hotel",
            "price": 1577,
            "rating": 8.4,
            "stars": 4
          },
          {
            "name": "Avani Central Busan",
            "price": 1688,
            "rating": 9.2,
            "stars": 4
          }
        ],
        [
          {
            "name": "ASTI Hotel Busan Station",
            "price": 1297,
            "rating": 9.2,
            "stars": 4
          },
          {
            "name": "Lavalse Hotel",
            "price": 1363,
            "rating": 8.4,
            "stars": 4
          }
        ]
      ]
    }
  ]
}